[
    {
        "text-index": 0,
        "sentence-length": 7,
        "z-score": -3.8729833462074166
    },
    {
        "text-index": 1,
        "sentence-length": 4,
        "z-score": -0.4472135954999579
    },
    {
        "text-index": 2,
        "sentence-length": 7,
        "z-score": -1.2909944487358056
    },
    {
        "text-index": 3,
        "sentence-length": 6,
        "z-score": -2.6457513110645903
    },
    {
        "text-index": 4,
        "sentence-length": 8,
        "z-score": 0
    },
    {
        "text-index": 5,
        "sentence-length": 15,
        "z-score": 0
    },
    {
        "text-index": 6,
        "sentence-length": 8,
        "z-score": 0
    },
    {
        "text-index": 7,
        "sentence-length": 7,
        "z-score": 0
    },
    {
        "text-index": 8,
        "sentence-length": 7,
        "z-score": 0
    },
    {
        "text-index": 9,
        "sentence-length": 7,
        "z-score": 0
    },
    {
        "text-index": 10,
        "sentence-length": 23,
        "z-score": 0
    },
    {
        "text-index": 11,
        "sentence-length": 10,
        "z-score": 0
    },
    {
        "text-index": 12,
        "sentence-length": 8,
        "z-score": 0
    },
    {
        "text-index": 13,
        "sentence-length": 7,
        "z-score": 0
    }
]